Metadata-Version: 2.1
Name: person-age
Version: 0.4.0
Summary: Our first super useful library
Home-page: UNKNOWN
Author: SDA
Author-email: mail@mail.com
License: UNKNOWN
Platform: UNKNOWN
Requires-Python: >=3.8
